{"meta": {"num_vars": 2, "num_constrs": 4, "num_edges": 7}, "nodes": {"vars": [{"id": "TemperatureChecks", "type": "var", "vtype": "I", "lb": 0.0, "ub": 0.0, "obj": 1.0}, {"id": "BloodTests", "type": "var", "vtype": "I", "lb": 0.0, "ub": 0.0, "obj": 1.0}], "constrs": [{"id": "MinBloodTests", "type": "constr", "sense": ">", "rhs": 45.0}, {"id": "TempCheckRatio", "type": "constr", "sense": ">", "rhs": 0.0}, {"id": "StaffMinutes", "type": "constr", "sense": "<", "rhs": 22000.0}, {"id": "__OBJ__", "type": "obj", "sense": "max", "rhs": 0.0}]}, "edges": [{"src": "MinBloodTests", "dst": "BloodTests", "coef": 1.0}, {"src": "TempCheckRatio", "dst": "TemperatureChecks", "coef": 1.0}, {"src": "TempCheckRatio", "dst": "BloodTests", "coef": -5.0}, {"src": "StaffMinutes", "dst": "TemperatureChecks", "coef": 2.0}, {"src": "StaffMinutes", "dst": "BloodTests", "coef": 10.0}, {"src": "__OBJ__", "dst": "TemperatureChecks", "coef": 1.0}, {"src": "__OBJ__", "dst": "BloodTests", "coef": 1.0}]}