{"meta": {"num_vars": 2, "num_constrs": 4, "num_edges": 8}, "nodes": {"vars": [{"id": "plane_trips", "type": "var", "vtype": "I", "lb": 0.0, "ub": 0.0, "obj": 1.0}, {"id": "truck_trips", "type": "var", "vtype": "I", "lb": 0.0, "ub": 0.0, "obj": 1.0}], "constrs": [{"id": "TireRequirement", "type": "constr", "sense": ">", "rhs": 200.0}, {"id": "Budget", "type": "constr", "sense": "<", "rhs": 22000.0}, {"id": "TripRatio", "type": "constr", "sense": "<", "rhs": 0.0}, {"id": "__OBJ__", "type": "obj", "sense": "min", "rhs": 0.0}]}, "edges": [{"src": "TireRequirement", "dst": "plane_trips", "coef": 10.0}, {"src": "TireRequirement", "dst": "truck_trips", "coef": 6.0}, {"src": "Budget", "dst": "plane_trips", "coef": 1000.0}, {"src": "Budget", "dst": "truck_trips", "coef": 700.0}, {"src": "TripRatio", "dst": "plane_trips", "coef": 1.0}, {"src": "TripRatio", "dst": "truck_trips", "coef": -1.0}, {"src": "__OBJ__", "dst": "plane_trips", "coef": 1.0}, {"src": "__OBJ__", "dst": "truck_trips", "coef": 1.0}]}