{"meta": {"num_vars": 2, "num_constrs": 4, "num_edges": 7}, "nodes": {"vars": [{"id": "CalciumPills", "type": "var", "vtype": "I", "lb": 0.0, "ub": 0.0, "obj": 5.0}, {"id": "VitaminDPills", "type": "var", "vtype": "I", "lb": 0.0, "ub": 0.0, "obj": 6.0}], "constrs": [{"id": "TotalPills", "type": "constr", "sense": ">", "rhs": 130.0}, {"id": "MinVitaminD", "type": "constr", "sense": ">", "rhs": 40.0}, {"id": "CalciumMoreThanVitaminD", "type": "constr", "sense": ">", "rhs": 1.0}, {"id": "__OBJ__", "type": "obj", "sense": "min", "rhs": 0.0}]}, "edges": [{"src": "TotalPills", "dst": "CalciumPills", "coef": 1.0}, {"src": "TotalPills", "dst": "VitaminDPills", "coef": 1.0}, {"src": "MinVitaminD", "dst": "VitaminDPills", "coef": 1.0}, {"src": "CalciumMoreThanVitaminD", "dst": "CalciumPills", "coef": 1.0}, {"src": "CalciumMoreThanVitaminD", "dst": "VitaminDPills", "coef": -1.0}, {"src": "__OBJ__", "dst": "CalciumPills", "coef": 5.0}, {"src": "__OBJ__", "dst": "VitaminDPills", "coef": 6.0}]}